{
	"network": {
		"items": [
			{
				"id": 97,
				"label": "amo, a",
				"x": -0.2606,
				"y": 0.8267,
				"cluster": 4,
				"weights": {
					"Links": 7.0000,
					"Total link strength": 71.0000,
					"Documents": 29.0000,
					"Citations": 2305.0000,
					"Norm. citations": 67.0769
				},
				"scores": {
					"Avg. pub. year": 2012.0000,
					"Avg. citations": 79.4828,
					"Avg. norm. citations": 2.3130
				}
			},
			{
				"id": 182,
				"label": "aspect, a",
				"x": -0.1170,
				"y": -0.3235,
				"cluster": 2,
				"weights": {
					"Links": 15.0000,
					"Total link strength": 58.0000,
					"Documents": 34.0000,
					"Citations": 3034.0000,
					"Norm. citations": 80.5599
				},
				"scores": {
					"Avg. pub. year": 1991.5294,
					"Avg. citations": 89.2353,
					"Avg. norm. citations": 2.3694
				}
			},
			{
				"id": 453,
				"label": "beugnon, j",
				"x": 0.4596,
				"y": -0.4003,
				"cluster": 1,
				"weights": {
					"Links": 5.0000,
					"Total link strength": 37.0000,
					"Documents": 24.0000,
					"Citations": 867.0000,
					"Norm. citations": 45.8370
				},
				"scores": {
					"Avg. pub. year": 2017.1667,
					"Avg. citations": 36.1250,
					"Avg. norm. citations": 1.9099
				}
			},
			{
				"id": 490,
				"label": "biraben, f",
				"x": -0.8024,
				"y": 0.0866,
				"cluster": 3,
				"weights": {
					"Links": 17.0000,
					"Total link strength": 336.0000,
					"Documents": 141.0000,
					"Citations": 4659.0000,
					"Norm. citations": 115.2938
				},
				"scores": {
					"Avg. pub. year": 1995.3759,
					"Avg. citations": 33.0426,
					"Avg. norm. citations": 0.8177
				}
			},
			{
				"id": 501,
				"label": "bize, s",
				"x": 0.4372,
				"y": -0.6759,
				"cluster": 1,
				"weights": {
					"Links": 8.0000,
					"Total link strength": 63.0000,
					"Documents": 24.0000,
					"Citations": 1509.0000,
					"Norm. citations": 31.7781
				},
				"scores": {
					"Avg. pub. year": 2005.6667,
					"Avg. citations": 62.8750,
					"Avg. norm. citations": 1.3241
				}
			},
			{
				"id": 613,
				"label": "bouchaud, j",
				"x": -0.0249,
				"y": -0.5860,
				"cluster": 2,
				"weights": {
					"Links": 7.0000,
					"Total link strength": 19.0000,
					"Documents": 28.0000,
					"Citations": 1023.0000,
					"Norm. citations": 21.8919
				},
				"scores": {
					"Avg. pub. year": 1988.1429,
					"Avg. citations": 36.5357,
					"Avg. norm. citations": 0.7819
				}
			},
			{
				"id": 620,
				"label": "bouchiat, m",
				"x": -0.7036,
				"y": 0.3755,
				"cluster": 2,
				"weights": {
					"Links": 4.0000,
					"Total link strength": 41.0000,
					"Documents": 86.0000,
					"Citations": 3112.0000,
					"Norm. citations": 76.6350
				},
				"scores": {
					"Avg. pub. year": 1987.2209,
					"Avg. citations": 36.1860,
					"Avg. norm. citations": 0.8911
				}
			},
			{
				"id": 665,
				"label": "bramati, a",
				"x": -0.2922,
				"y": 0.6906,
				"cluster": 4,
				"weights": {
					"Links": 15.0000,
					"Total link strength": 278.0000,
					"Documents": 142.0000,
					"Citations": 4412.0000,
					"Norm. citations": 131.3249
				},
				"scores": {
					"Avg. pub. year": 2011.0775,
					"Avg. citations": 31.0704,
					"Avg. norm. citations": 0.9248
				}
			},
			{
				"id": 696,
				"label": "briant, t",
				"x": 0.5022,
				"y": 0.3412,
				"cluster": 5,
				"weights": {
					"Links": 5.0000,
					"Total link strength": 130.0000,
					"Documents": 55.0000,
					"Citations": 1683.0000,
					"Norm. citations": 37.8837
				},
				"scores": {
					"Avg. pub. year": 2010.3636,
					"Avg. citations": 30.6000,
					"Avg. norm. citations": 0.6888
				}
			},
			{
				"id": 709,
				"label": "brossel, j",
				"x": -0.4532,
				"y": -0.1431,
				"cluster": 2,
				"weights": {
					"Links": 7.0000,
					"Total link strength": 44.0000,
					"Documents": 77.0000,
					"Citations": 2207.0000,
					"Norm. citations": 72.0197
				},
				"scores": {
					"Avg. pub. year": 1961.3766,
					"Avg. citations": 28.6623,
					"Avg. norm. citations": 0.9353
				}
			},
			{
				"id": 718,
				"label": "brune, m",
				"x": 1.3220,
				"y": 0.1724,
				"cluster": 7,
				"weights": {
					"Links": 9.0000,
					"Total link strength": 358.0000,
					"Documents": 125.0000,
					"Citations": 15689.0000,
					"Norm. citations": 293.6514
				},
				"scores": {
					"Avg. pub. year": 2004.5120,
					"Avg. citations": 125.5120,
					"Avg. norm. citations": 2.3492
				}
			},
			{
				"id": 761,
				"label": "cagnac, b",
				"x": -0.5658,
				"y": 0.0313,
				"cluster": 3,
				"weights": {
					"Links": 8.0000,
					"Total link strength": 55.0000,
					"Documents": 36.0000,
					"Citations": 999.0000,
					"Norm. citations": 28.6136
				},
				"scores": {
					"Avg. pub. year": 1977.9167,
					"Avg. citations": 27.7500,
					"Avg. norm. citations": 0.7948
				}
			},
			{
				"id": 825,
				"label": "carusotto, i",
				"x": -0.2539,
				"y": 0.3008,
				"cluster": 4,
				"weights": {
					"Links": 10.0000,
					"Total link strength": 53.0000,
					"Documents": 37.0000,
					"Citations": 2326.0000,
					"Norm. citations": 55.8336
				},
				"scores": {
					"Avg. pub. year": 2006.0811,
					"Avg. citations": 62.8649,
					"Avg. norm. citations": 1.5090
				}
			},
			{
				"id": 847,
				"label": "castin, y",
				"x": 0.0876,
				"y": -0.4016,
				"cluster": 1,
				"weights": {
					"Links": 16.0000,
					"Total link strength": 89.0000,
					"Documents": 132.0000,
					"Citations": 11329.0000,
					"Norm. citations": 226.3557
				},
				"scores": {
					"Avg. pub. year": 2005.1515,
					"Avg. citations": 85.8258,
					"Avg. norm. citations": 1.7148
				}
			},
			{
				"id": 961,
				"label": "cherroret, n",
				"x": -0.4486,
				"y": -0.3091,
				"cluster": 8,
				"weights": {
					"Links": 11.0000,
					"Total link strength": 45.0000,
					"Documents": 32.0000,
					"Citations": 270.0000,
					"Norm. citations": 14.8704
				},
				"scores": {
					"Avg. pub. year": 2017.4688,
					"Avg. citations": 8.4375,
					"Avg. norm. citations": 0.4647
				}
			},
			{
				"id": 966,
				"label": "chevy, f",
				"x": 0.3265,
				"y": -0.5556,
				"cluster": 1,
				"weights": {
					"Links": 13.0000,
					"Total link strength": 66.0000,
					"Documents": 79.0000,
					"Citations": 6519.0000,
					"Norm. citations": 136.4748
				},
				"scores": {
					"Avg. pub. year": 2010.3038,
					"Avg. citations": 82.5190,
					"Avg. norm. citations": 1.7275
				}
			},
			{
				"id": 1010,
				"label": "clade, p",
				"x": -1.1314,
				"y": 0.1288,
				"cluster": 3,
				"weights": {
					"Links": 8.0000,
					"Total link strength": 131.0000,
					"Documents": 40.0000,
					"Citations": 1413.0000,
					"Norm. citations": 43.0554
				},
				"scores": {
					"Avg. pub. year": 2011.1750,
					"Avg. citations": 35.3250,
					"Avg. norm. citations": 1.0764
				}
			},
			{
				"id": 1031,
				"label": "cohadon, pf",
				"x": 0.5596,
				"y": 0.2291,
				"cluster": 5,
				"weights": {
					"Links": 4.0000,
					"Total link strength": 107.0000,
					"Documents": 49.0000,
					"Citations": 1317.0000,
					"Norm. citations": 29.7975
				},
				"scores": {
					"Avg. pub. year": 2012.5918,
					"Avg. citations": 26.8776,
					"Avg. norm. citations": 0.6081
				}
			},
			{
				"id": 1033,
				"label": "cohen-tannoudji, c",
				"x": 0.1799,
				"y": -0.2276,
				"cluster": 2,
				"weights": {
					"Links": 24.0000,
					"Total link strength": 158.0000,
					"Documents": 171.0000,
					"Citations": 11845.0000,
					"Norm. citations": 268.8782
				},
				"scores": {
					"Avg. pub. year": 1988.3450,
					"Avg. citations": 69.2690,
					"Avg. norm. citations": 1.5724
				}
			},
			{
				"id": 1096,
				"label": "coudreau, t",
				"x": 0.1469,
				"y": 0.7670,
				"cluster": 6,
				"weights": {
					"Links": 8.0000,
					"Total link strength": 67.0000,
					"Documents": 28.0000,
					"Citations": 653.0000,
					"Norm. citations": 13.6287
				},
				"scores": {
					"Avg. pub. year": 2003.8214,
					"Avg. citations": 23.3214,
					"Avg. norm. citations": 0.4867
				}
			},
			{
				"id": 1101,
				"label": "courtois, j",
				"x": -0.1717,
				"y": -0.0427,
				"cluster": 5,
				"weights": {
					"Links": 11.0000,
					"Total link strength": 65.0000,
					"Documents": 36.0000,
					"Citations": 1707.0000,
					"Norm. citations": 33.7959
				},
				"scores": {
					"Avg. pub. year": 1994.5556,
					"Avg. citations": 47.4167,
					"Avg. norm. citations": 0.9388
				}
			},
			{
				"id": 1102,
				"label": "courty, j",
				"x": 0.0867,
				"y": 0.2672,
				"cluster": 9,
				"weights": {
					"Links": 13.0000,
					"Total link strength": 59.0000,
					"Documents": 36.0000,
					"Citations": 874.0000,
					"Norm. citations": 16.1516
				},
				"scores": {
					"Avg. pub. year": 1997.5278,
					"Avg. citations": 24.2778,
					"Avg. norm. citations": 0.4487
				}
			},
			{
				"id": 1144,
				"label": "dahan, m",
				"x": 0.1077,
				"y": 0.3576,
				"cluster": 4,
				"weights": {
					"Links": 4.0000,
					"Total link strength": 19.0000,
					"Documents": 62.0000,
					"Citations": 5958.0000,
					"Norm. citations": 136.6510
				},
				"scores": {
					"Avg. pub. year": 2008.4032,
					"Avg. citations": 96.0968,
					"Avg. norm. citations": 2.2040
				}
			},
			{
				"id": 1148,
				"label": "dalibard, j",
				"x": 0.3235,
				"y": -0.3626,
				"cluster": 1,
				"weights": {
					"Links": 21.0000,
					"Total link strength": 172.0000,
					"Documents": 162.0000,
					"Citations": 24256.0000,
					"Norm. citations": 512.2271
				},
				"scores": {
					"Avg. pub. year": 2003.3519,
					"Avg. citations": 149.7284,
					"Avg. norm. citations": 3.1619
				}
			},
			{
				"id": 1163,
				"label": "dantan, a",
				"x": -0.0754,
				"y": 0.3855,
				"cluster": 5,
				"weights": {
					"Links": 8.0000,
					"Total link strength": 57.0000,
					"Documents": 26.0000,
					"Citations": 855.0000,
					"Norm. citations": 17.8675
				},
				"scores": {
					"Avg. pub. year": 2005.0769,
					"Avg. citations": 32.8846,
					"Avg. norm. citations": 0.6872
				}
			},
			{
				"id": 1243,
				"label": "delande, d",
				"x": -0.6015,
				"y": -0.3531,
				"cluster": 8,
				"weights": {
					"Links": 10.0000,
					"Total link strength": 108.0000,
					"Documents": 200.0000,
					"Citations": 5972.0000,
					"Norm. citations": 157.0781
				},
				"scores": {
					"Avg. pub. year": 2003.2150,
					"Avg. citations": 29.8600,
					"Avg. norm. citations": 0.7854
				}
			},
			{
				"id": 1248,
				"label": "deleglise, s",
				"x": 0.8078,
				"y": 0.1929,
				"cluster": 5,
				"weights": {
					"Links": 10.0000,
					"Total link strength": 107.0000,
					"Documents": 31.0000,
					"Citations": 1491.0000,
					"Norm. citations": 32.4988
				},
				"scores": {
					"Avg. pub. year": 2013.6452,
					"Avg. citations": 48.0968,
					"Avg. norm. citations": 1.0483
				}
			},
			{
				"id": 1279,
				"label": "desbiolles, p",
				"x": 0.3135,
				"y": -0.0630,
				"cluster": 1,
				"weights": {
					"Links": 8.0000,
					"Total link strength": 33.0000,
					"Documents": 34.0000,
					"Citations": 1965.0000,
					"Norm. citations": 37.8115
				},
				"scores": {
					"Avg. pub. year": 2003.1176,
					"Avg. citations": 57.7941,
					"Avg. norm. citations": 1.1121
				}
			},
			{
				"id": 1380,
				"label": "dotsenko, i",
				"x": 1.2443,
				"y": -0.0212,
				"cluster": 7,
				"weights": {
					"Links": 8.0000,
					"Total link strength": 127.0000,
					"Documents": 32.0000,
					"Citations": 1508.0000,
					"Norm. citations": 33.9585
				},
				"scores": {
					"Avg. pub. year": 2012.8125,
					"Avg. citations": 47.1250,
					"Avg. norm. citations": 1.0612
				}
			},
			{
				"id": 1444,
				"label": "dupontroc, j",
				"x": -0.0193,
				"y": -0.3418,
				"cluster": 2,
				"weights": {
					"Links": 9.0000,
					"Total link strength": 32.0000,
					"Documents": 28.0000,
					"Citations": 1294.0000,
					"Norm. citations": 35.3767
				},
				"scores": {
					"Avg. pub. year": 1985.7143,
					"Avg. citations": 46.2143,
					"Avg. norm. citations": 1.2635
				}
			},
			{
				"id": 1555,
				"label": "fabre, c",
				"x": 0.2699,
				"y": 0.6311,
				"cluster": 6,
				"weights": {
					"Links": 21.0000,
					"Total link strength": 338.0000,
					"Documents": 249.0000,
					"Citations": 7946.0000,
					"Norm. citations": 212.4901
				},
				"scores": {
					"Avg. pub. year": 2003.1847,
					"Avg. citations": 31.9116,
					"Avg. norm. citations": 0.8534
				}
			},
			{
				"id": 1836,
				"label": "gerbier, f",
				"x": 0.4963,
				"y": -0.3258,
				"cluster": 1,
				"weights": {
					"Links": 4.0000,
					"Total link strength": 29.0000,
					"Documents": 40.0000,
					"Citations": 3300.0000,
					"Norm. citations": 90.6463
				},
				"scores": {
					"Avg. pub. year": 2013.6750,
					"Avg. citations": 82.5000,
					"Avg. norm. citations": 2.2662
				}
			},
			{
				"id": 1860,
				"label": "giacobino, e",
				"x": -0.2131,
				"y": 0.5090,
				"cluster": 4,
				"weights": {
					"Links": 31.0000,
					"Total link strength": 435.0000,
					"Documents": 226.0000,
					"Citations": 8423.0000,
					"Norm. citations": 209.2632
				},
				"scores": {
					"Avg. pub. year": 2002.1947,
					"Avg. citations": 37.2699,
					"Avg. norm. citations": 0.9259
				}
			},
			{
				"id": 1870,
				"label": "gigan, s",
				"x": 0.1779,
				"y": 0.9267,
				"cluster": 6,
				"weights": {
					"Links": 3.0000,
					"Total link strength": 35.0000,
					"Documents": 101.0000,
					"Citations": 2666.0000,
					"Norm. citations": 140.6235
				},
				"scores": {
					"Avg. pub. year": 2016.0792,
					"Avg. citations": 26.3960,
					"Avg. norm. citations": 1.3923
				}
			},
			{
				"id": 1886,
				"label": "girard, b",
				"x": -0.7378,
				"y": -0.7883,
				"cluster": 2,
				"weights": {
					"Links": 1.0000,
					"Total link strength": 25.0000,
					"Documents": 26.0000,
					"Citations": 347.0000,
					"Norm. citations": 7.7512
				},
				"scores": {
					"Avg. pub. year": 1988.1538,
					"Avg. citations": 13.3462,
					"Avg. norm. citations": 0.2981
				}
			},
			{
				"id": 1900,
				"label": "gleyzes, s",
				"x": 1.3770,
				"y": 0.0125,
				"cluster": 7,
				"weights": {
					"Links": 8.0000,
					"Total link strength": 161.0000,
					"Documents": 39.0000,
					"Citations": 2262.0000,
					"Norm. citations": 62.6459
				},
				"scores": {
					"Avg. pub. year": 2011.4359,
					"Avg. citations": 58.0000,
					"Avg. norm. citations": 1.6063
				}
			},
			{
				"id": 1904,
				"label": "glorieux, q",
				"x": -0.4413,
				"y": 0.7673,
				"cluster": 4,
				"weights": {
					"Links": 8.0000,
					"Total link strength": 82.0000,
					"Documents": 35.0000,
					"Citations": 314.0000,
					"Norm. citations": 22.2077
				},
				"scores": {
					"Avg. pub. year": 2018.2857,
					"Avg. citations": 8.9714,
					"Avg. norm. citations": 0.6345
				}
			},
			{
				"id": 1988,
				"label": "gremaud, b",
				"x": -0.7784,
				"y": -0.3008,
				"cluster": 8,
				"weights": {
					"Links": 13.0000,
					"Total link strength": 100.0000,
					"Documents": 76.0000,
					"Citations": 1941.0000,
					"Norm. citations": 43.3372
				},
				"scores": {
					"Avg. pub. year": 2008.5263,
					"Avg. citations": 25.5395,
					"Avg. norm. citations": 0.5702
				}
			},
			{
				"id": 2023,
				"label": "grynberg, g",
				"x": -0.3107,
				"y": 0.0971,
				"cluster": 5,
				"weights": {
					"Links": 15.0000,
					"Total link strength": 220.0000,
					"Documents": 177.0000,
					"Citations": 5520.0000,
					"Norm. citations": 123.1867
				},
				"scores": {
					"Avg. pub. year": 1988.9153,
					"Avg. citations": 31.1864,
					"Avg. norm. citations": 0.6960
				}
			},
			{
				"id": 2033,
				"label": "guellati-khelifa, s",
				"x": -1.0294,
				"y": 0.2063,
				"cluster": 3,
				"weights": {
					"Links": 8.0000,
					"Total link strength": 123.0000,
					"Documents": 35.0000,
					"Citations": 1264.0000,
					"Norm. citations": 38.5314
				},
				"scores": {
					"Avg. pub. year": 2011.3429,
					"Avg. citations": 36.1143,
					"Avg. norm. citations": 1.1009
				}
			},
			{
				"id": 2038,
				"label": "guerlin, c",
				"x": 0.9072,
				"y": -0.2373,
				"cluster": 1,
				"weights": {
					"Links": 12.0000,
					"Total link strength": 64.0000,
					"Documents": 25.0000,
					"Citations": 1111.0000,
					"Norm. citations": 31.2432
				},
				"scores": {
					"Avg. pub. year": 2014.0400,
					"Avg. citations": 44.4400,
					"Avg. norm. citations": 1.2497
				}
			},
			{
				"id": 2041,
				"label": "guerout, r",
				"x": -0.0583,
				"y": -0.0903,
				"cluster": 9,
				"weights": {
					"Links": 5.0000,
					"Total link strength": 70.0000,
					"Documents": 41.0000,
					"Citations": 659.0000,
					"Norm. citations": 25.4240
				},
				"scores": {
					"Avg. pub. year": 2015.0244,
					"Avg. citations": 16.0732,
					"Avg. norm. citations": 0.6201
				}
			},
			{
				"id": 2043,
				"label": "guery-odelin, d",
				"x": 0.4232,
				"y": -0.2482,
				"cluster": 1,
				"weights": {
					"Links": 4.0000,
					"Total link strength": 20.0000,
					"Documents": 33.0000,
					"Citations": 1138.0000,
					"Norm. citations": 21.1045
				},
				"scores": {
					"Avg. pub. year": 2004.0303,
					"Avg. citations": 34.4848,
					"Avg. norm. citations": 0.6395
				}
			},
			{
				"id": 2135,
				"label": "hare, j",
				"x": 0.9124,
				"y": 0.0525,
				"cluster": 7,
				"weights": {
					"Links": 4.0000,
					"Total link strength": 33.0000,
					"Documents": 34.0000,
					"Citations": 1840.0000,
					"Norm. citations": 36.8370
				},
				"scores": {
					"Avg. pub. year": 1999.5882,
					"Avg. citations": 54.1176,
					"Avg. norm. citations": 1.0834
				}
			},
			{
				"id": 2139,
				"label": "haroche, s",
				"x": 1.0540,
				"y": 0.1370,
				"cluster": 7,
				"weights": {
					"Links": 13.0000,
					"Total link strength": 447.0000,
					"Documents": 245.0000,
					"Citations": 24667.0000,
					"Norm. citations": 500.4191
				},
				"scores": {
					"Avg. pub. year": 1994.6245,
					"Avg. citations": 100.6816,
					"Avg. norm. citations": 2.0425
				}
			},
			{
				"id": 2175,
				"label": "heidmann, a",
				"x": 0.3401,
				"y": 0.2757,
				"cluster": 5,
				"weights": {
					"Links": 16.0000,
					"Total link strength": 220.0000,
					"Documents": 106.0000,
					"Citations": 4298.0000,
					"Norm. citations": 91.6830
				},
				"scores": {
					"Avg. pub. year": 2002.3208,
					"Avg. citations": 40.5472,
					"Avg. norm. citations": 0.8649
				}
			},
			{
				"id": 2203,
				"label": "hermier, j",
				"x": -0.0148,
				"y": 0.4956,
				"cluster": 4,
				"weights": {
					"Links": 5.0000,
					"Total link strength": 40.0000,
					"Documents": 21.0000,
					"Citations": 1052.0000,
					"Norm. citations": 19.7679
				},
				"scores": {
					"Avg. pub. year": 2002.1905,
					"Avg. citations": 50.0952,
					"Avg. norm. citations": 0.9413
				}
			},
			{
				"id": 2223,
				"label": "hilico, l",
				"x": -0.6154,
				"y": 0.1988,
				"cluster": 3,
				"weights": {
					"Links": 16.0000,
					"Total link strength": 108.0000,
					"Documents": 66.0000,
					"Citations": 1857.0000,
					"Norm. citations": 49.6407
				},
				"scores": {
					"Avg. pub. year": 2006.5606,
					"Avg. citations": 28.1364,
					"Avg. norm. citations": 0.7521
				}
			},
			{
				"id": 2342,
				"label": "indelicato, p",
				"x": -1.2495,
				"y": -0.1086,
				"cluster": 3,
				"weights": {
					"Links": 5.0000,
					"Total link strength": 43.0000,
					"Documents": 374.0000,
					"Citations": 9100.0000,
					"Norm. citations": 234.8756
				},
				"scores": {
					"Avg. pub. year": 2004.6818,
					"Avg. citations": 24.3316,
					"Avg. norm. citations": 0.6280
				}
			},
			{
				"id": 2381,
				"label": "jacquier, p",
				"x": -0.7786,
				"y": 0.4805,
				"cluster": 2,
				"weights": {
					"Links": 1.0000,
					"Total link strength": 27.0000,
					"Documents": 38.0000,
					"Citations": 345.0000,
					"Norm. citations": 7.5946
				},
				"scores": {
					"Avg. pub. year": 1999.0000,
					"Avg. citations": 9.0789,
					"Avg. norm. citations": 0.1999
				}
			},
			{
				"id": 2493,
				"label": "julien, l",
				"x": -0.8959,
				"y": -0.0753,
				"cluster": 3,
				"weights": {
					"Links": 14.0000,
					"Total link strength": 230.0000,
					"Documents": 83.0000,
					"Citations": 2258.0000,
					"Norm. citations": 54.2253
				},
				"scores": {
					"Avg. pub. year": 1998.6506,
					"Avg. citations": 27.2048,
					"Avg. norm. citations": 0.6533
				}
			},
			{
				"id": 2511,
				"label": "kaiser, r",
				"x": -0.3901,
				"y": -0.4014,
				"cluster": 8,
				"weights": {
					"Links": 12.0000,
					"Total link strength": 50.0000,
					"Documents": 27.0000,
					"Citations": 1843.0000,
					"Norm. citations": 42.4705
				},
				"scores": {
					"Avg. pub. year": 2001.6667,
					"Avg. citations": 68.2593,
					"Avg. norm. citations": 1.5730
				}
			},
			{
				"id": 2536,
				"label": "karr, jp",
				"x": -0.5772,
				"y": 0.3513,
				"cluster": 3,
				"weights": {
					"Links": 6.0000,
					"Total link strength": 45.0000,
					"Documents": 49.0000,
					"Citations": 1252.0000,
					"Norm. citations": 46.8869
				},
				"scores": {
					"Avg. pub. year": 2013.9388,
					"Avg. citations": 25.5510,
					"Avg. norm. citations": 0.9569
				}
			},
			{
				"id": 2548,
				"label": "kastler, a",
				"x": -0.3529,
				"y": -0.2082,
				"cluster": 2,
				"weights": {
					"Links": 4.0000,
					"Total link strength": 21.0000,
					"Documents": 179.0000,
					"Citations": 3036.0000,
					"Norm. citations": 123.7704
				},
				"scores": {
					"Avg. pub. year": 1974.5866,
					"Avg. citations": 16.9609,
					"Avg. norm. citations": 0.6915
				}
			},
			{
				"id": 2792,
				"label": "laloe, f",
				"x": -0.2068,
				"y": -0.4694,
				"cluster": 2,
				"weights": {
					"Links": 16.0000,
					"Total link strength": 111.0000,
					"Documents": 200.0000,
					"Citations": 3841.0000,
					"Norm. citations": 97.5624
				},
				"scores": {
					"Avg. pub. year": 1996.4550,
					"Avg. citations": 19.2050,
					"Avg. norm. citations": 0.4878
				}
			},
			{
				"id": 2797,
				"label": "lambrecht, a",
				"x": 0.0559,
				"y": -0.0443,
				"cluster": 9,
				"weights": {
					"Links": 11.0000,
					"Total link strength": 158.0000,
					"Documents": 137.0000,
					"Citations": 3900.0000,
					"Norm. citations": 83.7061
				},
				"scores": {
					"Avg. pub. year": 2007.9781,
					"Avg. citations": 28.4672,
					"Avg. norm. citations": 0.6110
				}
			},
			{
				"id": 2838,
				"label": "laurat, j",
				"x": 0.0350,
				"y": 0.8728,
				"cluster": 6,
				"weights": {
					"Links": 9.0000,
					"Total link strength": 105.0000,
					"Documents": 93.0000,
					"Citations": 2260.0000,
					"Norm. citations": 78.4759
				},
				"scores": {
					"Avg. pub. year": 2013.3333,
					"Avg. citations": 24.3011,
					"Avg. norm. citations": 0.8438
				}
			},
			{
				"id": 2842,
				"label": "laurent, p",
				"x": 0.2456,
				"y": -0.7691,
				"cluster": 1,
				"weights": {
					"Links": 11.0000,
					"Total link strength": 79.0000,
					"Documents": 36.0000,
					"Citations": 3043.0000,
					"Norm. citations": 61.0030
				},
				"scores": {
					"Avg. pub. year": 2004.9167,
					"Avg. citations": 84.5278,
					"Avg. norm. citations": 1.6945
				}
			},
			{
				"id": 2854,
				"label": "le bigot, eo",
				"x": -1.3582,
				"y": -0.1482,
				"cluster": 3,
				"weights": {
					"Links": 1.0000,
					"Total link strength": 23.0000,
					"Documents": 26.0000,
					"Citations": 348.0000,
					"Norm. citations": 8.5839
				},
				"scores": {
					"Avg. pub. year": 2010.4231,
					"Avg. citations": 13.3846,
					"Avg. norm. citations": 0.3301
				}
			},
			{
				"id": 2891,
				"label": "leduc, m",
				"x": -0.1758,
				"y": -0.5940,
				"cluster": 2,
				"weights": {
					"Links": 14.0000,
					"Total link strength": 113.0000,
					"Documents": 105.0000,
					"Citations": 2252.0000,
					"Norm. citations": 50.9012
				},
				"scores": {
					"Avg. pub. year": 1989.4857,
					"Avg. citations": 21.4476,
					"Avg. norm. citations": 0.4848
				}
			},
			{
				"id": 2932,
				"label": "lemonde, p",
				"x": 0.3658,
				"y": -0.7720,
				"cluster": 1,
				"weights": {
					"Links": 11.0000,
					"Total link strength": 76.0000,
					"Documents": 28.0000,
					"Citations": 2326.0000,
					"Norm. citations": 41.8620
				},
				"scores": {
					"Avg. pub. year": 2003.2857,
					"Avg. citations": 83.0714,
					"Avg. norm. citations": 1.4951
				}
			},
			{
				"id": 2982,
				"label": "lhuillier, c",
				"x": -0.0672,
				"y": -0.6909,
				"cluster": 2,
				"weights": {
					"Links": 5.0000,
					"Total link strength": 19.0000,
					"Documents": 34.0000,
					"Citations": 823.0000,
					"Norm. citations": 18.9874
				},
				"scores": {
					"Avg. pub. year": 1983.6176,
					"Avg. citations": 24.2059,
					"Avg. norm. citations": 0.5585
				}
			},
			{
				"id": 3163,
				"label": "maitre, a",
				"x": -0.0036,
				"y": 0.7296,
				"cluster": 6,
				"weights": {
					"Links": 16.0000,
					"Total link strength": 134.0000,
					"Documents": 53.0000,
					"Citations": 1263.0000,
					"Norm. citations": 29.5812
				},
				"scores": {
					"Avg. pub. year": 2005.5094,
					"Avg. citations": 23.8302,
					"Avg. norm. citations": 0.5581
				}
			},
			{
				"id": 3390,
				"label": "miniatura, c",
				"x": -0.6704,
				"y": -0.4664,
				"cluster": 8,
				"weights": {
					"Links": 6.0000,
					"Total link strength": 82.0000,
					"Documents": 51.0000,
					"Citations": 1332.0000,
					"Norm. citations": 32.7636
				},
				"scores": {
					"Avg. pub. year": 2009.6667,
					"Avg. citations": 26.1176,
					"Avg. norm. citations": 0.6424
				}
			},
			{
				"id": 3536,
				"label": "nacher, pj",
				"x": -0.2774,
				"y": -0.7202,
				"cluster": 2,
				"weights": {
					"Links": 7.0000,
					"Total link strength": 123.0000,
					"Documents": 106.0000,
					"Citations": 1683.0000,
					"Norm. citations": 40.9721
				},
				"scores": {
					"Avg. pub. year": 1997.1415,
					"Avg. citations": 15.8774,
					"Avg. norm. citations": 0.3865
				}
			},
			{
				"id": 3558,
				"label": "nascimbene, s",
				"x": 0.4117,
				"y": -0.4930,
				"cluster": 1,
				"weights": {
					"Links": 6.0000,
					"Total link strength": 49.0000,
					"Documents": 38.0000,
					"Citations": 3748.0000,
					"Norm. citations": 121.2964
				},
				"scores": {
					"Avg. pub. year": 2015.9737,
					"Avg. citations": 98.6316,
					"Avg. norm. citations": 3.1920
				}
			},
			{
				"id": 3584,
				"label": "nez, f",
				"x": -1.0279,
				"y": 0.0170,
				"cluster": 3,
				"weights": {
					"Links": 13.0000,
					"Total link strength": 242.0000,
					"Documents": 87.0000,
					"Citations": 2926.0000,
					"Norm. citations": 69.8611
				},
				"scores": {
					"Avg. pub. year": 2005.8391,
					"Avg. citations": 33.6322,
					"Avg. norm. citations": 0.8030
				}
			},
			{
				"id": 3616,
				"label": "nogues, g",
				"x": 1.3860,
				"y": 0.3400,
				"cluster": 7,
				"weights": {
					"Links": 5.0000,
					"Total link strength": 91.0000,
					"Documents": 28.0000,
					"Citations": 3541.0000,
					"Norm. citations": 61.1566
				},
				"scores": {
					"Avg. pub. year": 2003.7500,
					"Avg. citations": 126.4643,
					"Avg. norm. citations": 2.1842
				}
			},
			{
				"id": 3757,
				"label": "parigi, v",
				"x": 0.3651,
				"y": 1.0340,
				"cluster": 6,
				"weights": {
					"Links": 4.0000,
					"Total link strength": 34.0000,
					"Documents": 23.0000,
					"Citations": 310.0000,
					"Norm. citations": 24.1713
				},
				"scores": {
					"Avg. pub. year": 2019.1304,
					"Avg. citations": 13.4783,
					"Avg. norm. citations": 1.0509
				}
			},
			{
				"id": 3911,
				"label": "pigeon, s",
				"x": -0.4517,
				"y": 0.6400,
				"cluster": 4,
				"weights": {
					"Links": 8.0000,
					"Total link strength": 86.0000,
					"Documents": 29.0000,
					"Citations": 1307.0000,
					"Norm. citations": 43.4727
				},
				"scores": {
					"Avg. pub. year": 2016.7241,
					"Avg. citations": 45.0690,
					"Avg. norm. citations": 1.4991
				}
			},
			{
				"id": 3922,
				"label": "pinard, m",
				"x": -0.0811,
				"y": 0.2200,
				"cluster": 5,
				"weights": {
					"Links": 20.0000,
					"Total link strength": 229.0000,
					"Documents": 139.0000,
					"Citations": 4491.0000,
					"Norm. citations": 92.0376
				},
				"scores": {
					"Avg. pub. year": 1994.6835,
					"Avg. citations": 32.3094,
					"Avg. norm. citations": 0.6621
				}
			},
			{
				"id": 3939,
				"label": "pisanello, f",
				"x": -0.3587,
				"y": 0.8641,
				"cluster": 4,
				"weights": {
					"Links": 7.0000,
					"Total link strength": 46.0000,
					"Documents": 27.0000,
					"Citations": 746.0000,
					"Norm. citations": 17.1409
				},
				"scores": {
					"Avg. pub. year": 2012.0370,
					"Avg. citations": 27.6296,
					"Avg. norm. citations": 0.6348
				}
			},
			{
				"id": 4068,
				"label": "raimond, jm",
				"x": 1.1690,
				"y": 0.3057,
				"cluster": 7,
				"weights": {
					"Links": 12.0000,
					"Total link strength": 435.0000,
					"Documents": 186.0000,
					"Citations": 19501.0000,
					"Norm. citations": 379.1865
				},
				"scores": {
					"Avg. pub. year": 2000.8226,
					"Avg. citations": 104.8441,
					"Avg. norm. citations": 2.0386
				}
			},
			{
				"id": 4126,
				"label": "reichel, j",
				"x": 0.5682,
				"y": -0.5895,
				"cluster": 1,
				"weights": {
					"Links": 9.0000,
					"Total link strength": 41.0000,
					"Documents": 82.0000,
					"Citations": 4261.0000,
					"Norm. citations": 114.7631
				},
				"scores": {
					"Avg. pub. year": 2011.3049,
					"Avg. citations": 51.9634,
					"Avg. norm. citations": 1.3995
				}
			},
			{
				"id": 4169,
				"label": "reynaud, s",
				"x": 0.1565,
				"y": 0.0535,
				"cluster": 9,
				"weights": {
					"Links": 24.0000,
					"Total link strength": 265.0000,
					"Documents": 216.0000,
					"Citations": 7966.0000,
					"Norm. citations": 183.5357
				},
				"scores": {
					"Avg. pub. year": 2002.0231,
					"Avg. citations": 36.8796,
					"Avg. norm. citations": 0.8497
				}
			},
			{
				"id": 4266,
				"label": "rosenbusch, p",
				"x": 0.5492,
				"y": -0.6798,
				"cluster": 1,
				"weights": {
					"Links": 13.0000,
					"Total link strength": 59.0000,
					"Documents": 31.0000,
					"Citations": 1055.0000,
					"Norm. citations": 25.7785
				},
				"scores": {
					"Avg. pub. year": 2008.9032,
					"Avg. citations": 34.0323,
					"Avg. norm. citations": 0.8316
				}
			},
			{
				"id": 4371,
				"label": "salomon, c",
				"x": 0.2034,
				"y": -0.5819,
				"cluster": 1,
				"weights": {
					"Links": 23.0000,
					"Total link strength": 210.0000,
					"Documents": 142.0000,
					"Citations": 13187.0000,
					"Norm. citations": 278.1756
				},
				"scores": {
					"Avg. pub. year": 2004.1408,
					"Avg. citations": 92.8662,
					"Avg. norm. citations": 1.9590
				}
			},
			{
				"id": 4430,
				"label": "sayrin, c",
				"x": 1.1356,
				"y": -0.0629,
				"cluster": 7,
				"weights": {
					"Links": 7.0000,
					"Total link strength": 100.0000,
					"Documents": 23.0000,
					"Citations": 1585.0000,
					"Norm. citations": 36.5225
				},
				"scores": {
					"Avg. pub. year": 2012.3478,
					"Avg. citations": 68.9130,
					"Avg. norm. citations": 1.5879
				}
			},
			{
				"id": 4525,
				"label": "schwob, c",
				"x": -0.8800,
				"y": 0.2550,
				"cluster": 3,
				"weights": {
					"Links": 11.0000,
					"Total link strength": 125.0000,
					"Documents": 32.0000,
					"Citations": 1212.0000,
					"Norm. citations": 21.8112
				},
				"scores": {
					"Avg. pub. year": 2002.6875,
					"Avg. citations": 37.8750,
					"Avg. norm. citations": 0.6816
				}
			},
			{
				"id": 4584,
				"label": "sheremet, as",
				"x": -0.0917,
				"y": 0.9302,
				"cluster": 6,
				"weights": {
					"Links": 3.0000,
					"Total link strength": 29.0000,
					"Documents": 20.0000,
					"Citations": 452.0000,
					"Norm. citations": 24.1981
				},
				"scores": {
					"Avg. pub. year": 2015.7500,
					"Avg. citations": 22.6000,
					"Avg. norm. citations": 1.2099
				}
			},
			{
				"id": 4593,
				"label": "shlyapnikov, g",
				"x": 0.3330,
				"y": -0.6466,
				"cluster": 1,
				"weights": {
					"Links": 7.0000,
					"Total link strength": 21.0000,
					"Documents": 29.0000,
					"Citations": 4212.0000,
					"Norm. citations": 75.6185
				},
				"scores": {
					"Avg. pub. year": 2002.2069,
					"Avg. citations": 145.2414,
					"Avg. norm. citations": 2.6075
				}
			},
			{
				"id": 4640,
				"label": "sinatra, a",
				"x": -0.0015,
				"y": -0.4954,
				"cluster": 1,
				"weights": {
					"Links": 14.0000,
					"Total link strength": 54.0000,
					"Documents": 52.0000,
					"Citations": 2049.0000,
					"Norm. citations": 49.7500
				},
				"scores": {
					"Avg. pub. year": 2009.6667,
					"Avg. citations": 39.4038,
					"Avg. norm. citations": 0.9567
				}
			},
			{
				"id": 4901,
				"label": "tastevin, g",
				"x": -0.2362,
				"y": -0.8277,
				"cluster": 2,
				"weights": {
					"Links": 4.0000,
					"Total link strength": 87.0000,
					"Documents": 64.0000,
					"Citations": 928.0000,
					"Norm. citations": 20.7073
				},
				"scores": {
					"Avg. pub. year": 2000.5469,
					"Avg. citations": 14.5000,
					"Avg. norm. citations": 0.3236
				}
			},
			{
				"id": 5028,
				"label": "treps, n",
				"x": 0.3077,
				"y": 0.8505,
				"cluster": 6,
				"weights": {
					"Links": 12.0000,
					"Total link strength": 213.0000,
					"Documents": 167.0000,
					"Citations": 3508.0000,
					"Norm. citations": 117.2225
				},
				"scores": {
					"Avg. pub. year": 2012.5868,
					"Avg. citations": 21.0060,
					"Avg. norm. citations": 0.7019
				}
			},
			{
				"id": 5158,
				"label": "verkerk, p",
				"x": -0.2828,
				"y": -0.0601,
				"cluster": 5,
				"weights": {
					"Links": 8.0000,
					"Total link strength": 76.0000,
					"Documents": 48.0000,
					"Citations": 1653.0000,
					"Norm. citations": 33.9800
				},
				"scores": {
					"Avg. pub. year": 1991.4792,
					"Avg. citations": 34.4375,
					"Avg. norm. citations": 0.7079
				}
			},
			{
				"id": 5189,
				"label": "vigue, j",
				"x": -0.6801,
				"y": -0.7028,
				"cluster": 2,
				"weights": {
					"Links": 6.0000,
					"Total link strength": 34.0000,
					"Documents": 64.0000,
					"Citations": 1660.0000,
					"Norm. citations": 49.6656
				},
				"scores": {
					"Avg. pub. year": 1984.9688,
					"Avg. citations": 25.9375,
					"Avg. norm. citations": 0.7760
				}
			},
			{
				"id": 5268,
				"label": "walschaers, m",
				"x": 0.4410,
				"y": 0.9899,
				"cluster": 6,
				"weights": {
					"Links": 3.0000,
					"Total link strength": 37.0000,
					"Documents": 32.0000,
					"Citations": 301.0000,
					"Norm. citations": 29.5122
				},
				"scores": {
					"Avg. pub. year": 2019.5312,
					"Avg. citations": 9.4062,
					"Avg. norm. citations": 0.9223
				}
			},
			{
				"id": 5327,
				"label": "werner, f",
				"x": 0.0824,
				"y": -0.5313,
				"cluster": 1,
				"weights": {
					"Links": 3.0000,
					"Total link strength": 10.0000,
					"Documents": 23.0000,
					"Citations": 1402.0000,
					"Norm. citations": 41.3464
				},
				"scores": {
					"Avg. pub. year": 2012.3478,
					"Avg. citations": 60.9565,
					"Avg. norm. citations": 1.7977
				}
			},
			{
				"id": 5386,
				"label": "wolf, p",
				"x": 0.5422,
				"y": -0.4598,
				"cluster": 1,
				"weights": {
					"Links": 9.0000,
					"Total link strength": 61.0000,
					"Documents": 28.0000,
					"Citations": 913.0000,
					"Norm. citations": 26.5266
				},
				"scores": {
					"Avg. pub. year": 2012.1429,
					"Avg. citations": 32.6071,
					"Avg. norm. citations": 0.9474
				}
			}
		],
		"links": [
			{
				"source_id": 97,
				"target_id": 665,
				"strength": 22.0000
			},
			{
				"source_id": 97,
				"target_id": 825,
				"strength": 8.0000
			},
			{
				"source_id": 97,
				"target_id": 1860,
				"strength": 22.0000
			},
			{
				"source_id": 97,
				"target_id": 1904,
				"strength": 2.0000
			},
			{
				"source_id": 97,
				"target_id": 3163,
				"strength": 2.0000
			},
			{
				"source_id": 97,
				"target_id": 3911,
				"strength": 10.0000
			},
			{
				"source_id": 97,
				"target_id": 3939,
				"strength": 5.0000
			},
			{
				"source_id": 182,
				"target_id": 613,
				"strength": 2.0000
			},
			{
				"source_id": 182,
				"target_id": 847,
				"strength": 1.0000
			},
			{
				"source_id": 182,
				"target_id": 1033,
				"strength": 15.0000
			},
			{
				"source_id": 182,
				"target_id": 1101,
				"strength": 2.0000
			},
			{
				"source_id": 182,
				"target_id": 1102,
				"strength": 2.0000
			},
			{
				"source_id": 182,
				"target_id": 1148,
				"strength": 5.0000
			},
			{
				"source_id": 182,
				"target_id": 1243,
				"strength": 3.0000
			},
			{
				"source_id": 182,
				"target_id": 1988,
				"strength": 1.0000
			},
			{
				"source_id": 182,
				"target_id": 2175,
				"strength": 3.0000
			},
			{
				"source_id": 182,
				"target_id": 2511,
				"strength": 8.0000
			},
			{
				"source_id": 182,
				"target_id": 2891,
				"strength": 2.0000
			},
			{
				"source_id": 182,
				"target_id": 3390,
				"strength": 1.0000
			},
			{
				"source_id": 182,
				"target_id": 4169,
				"strength": 3.0000
			},
			{
				"source_id": 182,
				"target_id": 4371,
				"strength": 5.0000
			},
			{
				"source_id": 182,
				"target_id": 5189,
				"strength": 5.0000
			},
			{
				"source_id": 453,
				"target_id": 961,
				"strength": 1.0000
			},
			{
				"source_id": 453,
				"target_id": 1148,
				"strength": 13.0000
			},
			{
				"source_id": 453,
				"target_id": 1243,
				"strength": 1.0000
			},
			{
				"source_id": 453,
				"target_id": 1836,
				"strength": 9.0000
			},
			{
				"source_id": 453,
				"target_id": 3558,
				"strength": 13.0000
			},
			{
				"source_id": 490,
				"target_id": 761,
				"strength": 18.0000
			},
			{
				"source_id": 490,
				"target_id": 1010,
				"strength": 28.0000
			},
			{
				"source_id": 490,
				"target_id": 1243,
				"strength": 6.0000
			},
			{
				"source_id": 490,
				"target_id": 1860,
				"strength": 22.0000
			},
			{
				"source_id": 490,
				"target_id": 1988,
				"strength": 5.0000
			},
			{
				"source_id": 490,
				"target_id": 2023,
				"strength": 31.0000
			},
			{
				"source_id": 490,
				"target_id": 2033,
				"strength": 26.0000
			},
			{
				"source_id": 490,
				"target_id": 2223,
				"strength": 14.0000
			},
			{
				"source_id": 490,
				"target_id": 2342,
				"strength": 8.0000
			},
			{
				"source_id": 490,
				"target_id": 2493,
				"strength": 72.0000
			},
			{
				"source_id": 490,
				"target_id": 2536,
				"strength": 1.0000
			},
			{
				"source_id": 490,
				"target_id": 2842,
				"strength": 1.0000
			},
			{
				"source_id": 490,
				"target_id": 3584,
				"strength": 75.0000
			},
			{
				"source_id": 490,
				"target_id": 3922,
				"strength": 1.0000
			},
			{
				"source_id": 490,
				"target_id": 4525,
				"strength": 25.0000
			},
			{
				"source_id": 490,
				"target_id": 5158,
				"strength": 2.0000
			},
			{
				"source_id": 490,
				"target_id": 5189,
				"strength": 1.0000
			},
			{
				"source_id": 501,
				"target_id": 2038,
				"strength": 4.0000
			},
			{
				"source_id": 501,
				"target_id": 2797,
				"strength": 3.0000
			},
			{
				"source_id": 501,
				"target_id": 2842,
				"strength": 11.0000
			},
			{
				"source_id": 501,
				"target_id": 2932,
				"strength": 13.0000
			},
			{
				"source_id": 501,
				"target_id": 4169,
				"strength": 1.0000
			},
			{
				"source_id": 501,
				"target_id": 4266,
				"strength": 5.0000
			},
			{
				"source_id": 501,
				"target_id": 4371,
				"strength": 17.0000
			},
			{
				"source_id": 501,
				"target_id": 5386,
				"strength": 9.0000
			},
			{
				"source_id": 613,
				"target_id": 1033,
				"strength": 2.0000
			},
			{
				"source_id": 613,
				"target_id": 1144,
				"strength": 1.0000
			},
			{
				"source_id": 613,
				"target_id": 1279,
				"strength": 1.0000
			},
			{
				"source_id": 613,
				"target_id": 2203,
				"strength": 1.0000
			},
			{
				"source_id": 613,
				"target_id": 2891,
				"strength": 1.0000
			},
			{
				"source_id": 613,
				"target_id": 2982,
				"strength": 11.0000
			},
			{
				"source_id": 620,
				"target_id": 709,
				"strength": 12.0000
			},
			{
				"source_id": 620,
				"target_id": 1033,
				"strength": 1.0000
			},
			{
				"source_id": 620,
				"target_id": 1860,
				"strength": 1.0000
			},
			{
				"source_id": 620,
				"target_id": 2381,
				"strength": 27.0000
			},
			{
				"source_id": 665,
				"target_id": 825,
				"strength": 8.0000
			},
			{
				"source_id": 665,
				"target_id": 1163,
				"strength": 14.0000
			},
			{
				"source_id": 665,
				"target_id": 1860,
				"strength": 108.0000
			},
			{
				"source_id": 665,
				"target_id": 1904,
				"strength": 31.0000
			},
			{
				"source_id": 665,
				"target_id": 2203,
				"strength": 11.0000
			},
			{
				"source_id": 665,
				"target_id": 2511,
				"strength": 1.0000
			},
			{
				"source_id": 665,
				"target_id": 2536,
				"strength": 5.0000
			},
			{
				"source_id": 665,
				"target_id": 2838,
				"strength": 6.0000
			},
			{
				"source_id": 665,
				"target_id": 3163,
				"strength": 11.0000
			},
			{
				"source_id": 665,
				"target_id": 3911,
				"strength": 23.0000
			},
			{
				"source_id": 665,
				"target_id": 3922,
				"strength": 15.0000
			},
			{
				"source_id": 665,
				"target_id": 3939,
				"strength": 21.0000
			},
			{
				"source_id": 665,
				"target_id": 4584,
				"strength": 1.0000
			},
			{
				"source_id": 665,
				"target_id": 5028,
				"strength": 1.0000
			},
			{
				"source_id": 696,
				"target_id": 1031,
				"strength": 44.0000
			},
			{
				"source_id": 696,
				"target_id": 1163,
				"strength": 1.0000
			},
			{
				"source_id": 696,
				"target_id": 1248,
				"strength": 17.0000
			},
			{
				"source_id": 696,
				"target_id": 2175,
				"strength": 53.0000
			},
			{
				"source_id": 696,
				"target_id": 3922,
				"strength": 15.0000
			},
			{
				"source_id": 709,
				"target_id": 761,
				"strength": 5.0000
			},
			{
				"source_id": 709,
				"target_id": 1033,
				"strength": 3.0000
			},
			{
				"source_id": 709,
				"target_id": 2548,
				"strength": 13.0000
			},
			{
				"source_id": 709,
				"target_id": 2792,
				"strength": 5.0000
			},
			{
				"source_id": 709,
				"target_id": 2891,
				"strength": 5.0000
			},
			{
				"source_id": 709,
				"target_id": 3536,
				"strength": 1.0000
			},
			{
				"source_id": 718,
				"target_id": 1248,
				"strength": 10.0000
			},
			{
				"source_id": 718,
				"target_id": 1380,
				"strength": 27.0000
			},
			{
				"source_id": 718,
				"target_id": 1900,
				"strength": 37.0000
			},
			{
				"source_id": 718,
				"target_id": 2038,
				"strength": 6.0000
			},
			{
				"source_id": 718,
				"target_id": 2135,
				"strength": 1.0000
			},
			{
				"source_id": 718,
				"target_id": 2139,
				"strength": 110.0000
			},
			{
				"source_id": 718,
				"target_id": 3616,
				"strength": 27.0000
			},
			{
				"source_id": 718,
				"target_id": 4068,
				"strength": 120.0000
			},
			{
				"source_id": 718,
				"target_id": 4430,
				"strength": 20.0000
			},
			{
				"source_id": 761,
				"target_id": 1860,
				"strength": 4.0000
			},
			{
				"source_id": 761,
				"target_id": 2023,
				"strength": 17.0000
			},
			{
				"source_id": 761,
				"target_id": 2223,
				"strength": 2.0000
			},
			{
				"source_id": 761,
				"target_id": 2493,
				"strength": 3.0000
			},
			{
				"source_id": 761,
				"target_id": 2548,
				"strength": 3.0000
			},
			{
				"source_id": 761,
				"target_id": 3584,
				"strength": 3.0000
			},
			{
				"source_id": 825,
				"target_id": 847,
				"strength": 13.0000
			},
			{
				"source_id": 825,
				"target_id": 1148,
				"strength": 3.0000
			},
			{
				"source_id": 825,
				"target_id": 1860,
				"strength": 8.0000
			},
			{
				"source_id": 825,
				"target_id": 1904,
				"strength": 1.0000
			},
			{
				"source_id": 825,
				"target_id": 3911,
				"strength": 8.0000
			},
			{
				"source_id": 825,
				"target_id": 3939,
				"strength": 2.0000
			},
			{
				"source_id": 825,
				"target_id": 4371,
				"strength": 1.0000
			},
			{
				"source_id": 825,
				"target_id": 4640,
				"strength": 1.0000
			},
			{
				"source_id": 847,
				"target_id": 966,
				"strength": 1.0000
			},
			{
				"source_id": 847,
				"target_id": 1033,
				"strength": 3.0000
			},
			{
				"source_id": 847,
				"target_id": 1148,
				"strength": 17.0000
			},
			{
				"source_id": 847,
				"target_id": 1836,
				"strength": 1.0000
			},
			{
				"source_id": 847,
				"target_id": 2511,
				"strength": 1.0000
			},
			{
				"source_id": 847,
				"target_id": 2842,
				"strength": 1.0000
			},
			{
				"source_id": 847,
				"target_id": 2891,
				"strength": 1.0000
			},
			{
				"source_id": 847,
				"target_id": 2932,
				"strength": 1.0000
			},
			{
				"source_id": 847,
				"target_id": 4126,
				"strength": 1.0000
			},
			{
				"source_id": 847,
				"target_id": 4266,
				"strength": 1.0000
			},
			{
				"source_id": 847,
				"target_id": 4371,
				"strength": 9.0000
			},
			{
				"source_id": 847,
				"target_id": 4593,
				"strength": 3.0000
			},
			{
				"source_id": 847,
				"target_id": 4640,
				"strength": 27.0000
			},
			{
				"source_id": 847,
				"target_id": 5327,
				"strength": 8.0000
			},
			{
				"source_id": 961,
				"target_id": 1148,
				"strength": 1.0000
			},
			{
				"source_id": 961,
				"target_id": 1243,
				"strength": 20.0000
			},
			{
				"source_id": 961,
				"target_id": 1988,
				"strength": 4.0000
			},
			{
				"source_id": 961,
				"target_id": 2041,
				"strength": 3.0000
			},
			{
				"source_id": 961,
				"target_id": 2511,
				"strength": 2.0000
			},
			{
				"source_id": 961,
				"target_id": 2797,
				"strength": 3.0000
			},
			{
				"source_id": 961,
				"target_id": 3390,
				"strength": 6.0000
			},
			{
				"source_id": 961,
				"target_id": 3558,
				"strength": 1.0000
			},
			{
				"source_id": 961,
				"target_id": 3911,
				"strength": 1.0000
			},
			{
				"source_id": 961,
				"target_id": 4169,
				"strength": 3.0000
			},
			{
				"source_id": 966,
				"target_id": 1148,
				"strength": 14.0000
			},
			{
				"source_id": 966,
				"target_id": 1279,
				"strength": 1.0000
			},
			{
				"source_id": 966,
				"target_id": 1988,
				"strength": 1.0000
			},
			{
				"source_id": 966,
				"target_id": 2023,
				"strength": 1.0000
			},
			{
				"source_id": 966,
				"target_id": 2043,
				"strength": 1.0000
			},
			{
				"source_id": 966,
				"target_id": 2932,
				"strength": 1.0000
			},
			{
				"source_id": 966,
				"target_id": 3390,
				"strength": 2.0000
			},
			{
				"source_id": 966,
				"target_id": 3558,
				"strength": 7.0000
			},
			{
				"source_id": 966,
				"target_id": 4266,
				"strength": 4.0000
			},
			{
				"source_id": 966,
				"target_id": 4371,
				"strength": 29.0000
			},
			{
				"source_id": 966,
				"target_id": 4593,
				"strength": 3.0000
			},
			{
				"source_id": 966,
				"target_id": 5327,
				"strength": 1.0000
			},
			{
				"source_id": 1010,
				"target_id": 1988,
				"strength": 5.0000
			},
			{
				"source_id": 1010,
				"target_id": 2033,
				"strength": 34.0000
			},
			{
				"source_id": 1010,
				"target_id": 2041,
				"strength": 2.0000
			},
			{
				"source_id": 1010,
				"target_id": 2493,
				"strength": 19.0000
			},
			{
				"source_id": 1010,
				"target_id": 3584,
				"strength": 27.0000
			},
			{
				"source_id": 1010,
				"target_id": 4169,
				"strength": 2.0000
			},
			{
				"source_id": 1010,
				"target_id": 4525,
				"strength": 14.0000
			},
			{
				"source_id": 1031,
				"target_id": 1248,
				"strength": 17.0000
			},
			{
				"source_id": 1031,
				"target_id": 2175,
				"strength": 42.0000
			},
			{
				"source_id": 1031,
				"target_id": 3922,
				"strength": 4.0000
			},
			{
				"source_id": 1033,
				"target_id": 1101,
				"strength": 1.0000
			},
			{
				"source_id": 1033,
				"target_id": 1102,
				"strength": 1.0000
			},
			{
				"source_id": 1033,
				"target_id": 1148,
				"strength": 19.0000
			},
			{
				"source_id": 1033,
				"target_id": 1279,
				"strength": 1.0000
			},
			{
				"source_id": 1033,
				"target_id": 1444,
				"strength": 9.0000
			},
			{
				"source_id": 1033,
				"target_id": 1555,
				"strength": 5.0000
			},
			{
				"source_id": 1033,
				"target_id": 1860,
				"strength": 1.0000
			},
			{
				"source_id": 1033,
				"target_id": 2023,
				"strength": 5.0000
			},
			{
				"source_id": 1033,
				"target_id": 2139,
				"strength": 20.0000
			},
			{
				"source_id": 1033,
				"target_id": 2175,
				"strength": 2.0000
			},
			{
				"source_id": 1033,
				"target_id": 2511,
				"strength": 5.0000
			},
			{
				"source_id": 1033,
				"target_id": 2548,
				"strength": 3.0000
			},
			{
				"source_id": 1033,
				"target_id": 2792,
				"strength": 6.0000
			},
			{
				"source_id": 1033,
				"target_id": 2891,
				"strength": 18.0000
			},
			{
				"source_id": 1033,
				"target_id": 4126,
				"strength": 1.0000
			},
			{
				"source_id": 1033,
				"target_id": 4169,
				"strength": 22.0000
			},
			{
				"source_id": 1033,
				"target_id": 4371,
				"strength": 10.0000
			},
			{
				"source_id": 1033,
				"target_id": 5158,
				"strength": 1.0000
			},
			{
				"source_id": 1033,
				"target_id": 5386,
				"strength": 4.0000
			},
			{
				"source_id": 1096,
				"target_id": 1102,
				"strength": 1.0000
			},
			{
				"source_id": 1096,
				"target_id": 1555,
				"strength": 24.0000
			},
			{
				"source_id": 1096,
				"target_id": 1860,
				"strength": 5.0000
			},
			{
				"source_id": 1096,
				"target_id": 2797,
				"strength": 3.0000
			},
			{
				"source_id": 1096,
				"target_id": 2838,
				"strength": 16.0000
			},
			{
				"source_id": 1096,
				"target_id": 3163,
				"strength": 6.0000
			},
			{
				"source_id": 1096,
				"target_id": 4169,
				"strength": 1.0000
			},
			{
				"source_id": 1096,
				"target_id": 5028,
				"strength": 11.0000
			},
			{
				"source_id": 1101,
				"target_id": 1102,
				"strength": 3.0000
			},
			{
				"source_id": 1101,
				"target_id": 1555,
				"strength": 1.0000
			},
			{
				"source_id": 1101,
				"target_id": 2023,
				"strength": 30.0000
			},
			{
				"source_id": 1101,
				"target_id": 2511,
				"strength": 1.0000
			},
			{
				"source_id": 1101,
				"target_id": 3163,
				"strength": 2.0000
			},
			{
				"source_id": 1101,
				"target_id": 3922,
				"strength": 3.0000
			},
			{
				"source_id": 1101,
				"target_id": 4169,
				"strength": 3.0000
			},
			{
				"source_id": 1101,
				"target_id": 4371,
				"strength": 8.0000
			},
			{
				"source_id": 1101,
				"target_id": 5158,
				"strength": 11.0000
			},
			{
				"source_id": 1102,
				"target_id": 1555,
				"strength": 5.0000
			},
			{
				"source_id": 1102,
				"target_id": 1860,
				"strength": 11.0000
			},
			{
				"source_id": 1102,
				"target_id": 2175,
				"strength": 6.0000
			},
			{
				"source_id": 1102,
				"target_id": 2223,
				"strength": 2.0000
			},
			{
				"source_id": 1102,
				"target_id": 2797,
				"strength": 8.0000
			},
			{
				"source_id": 1102,
				"target_id": 3163,
				"strength": 1.0000
			},
			{
				"source_id": 1102,
				"target_id": 3922,
				"strength": 6.0000
			},
			{
				"source_id": 1102,
				"target_id": 4169,
				"strength": 12.0000
			},
			{
				"source_id": 1102,
				"target_id": 5028,
				"strength": 1.0000
			},
			{
				"source_id": 1144,
				"target_id": 1279,
				"strength": 6.0000
			},
			{
				"source_id": 1144,
				"target_id": 1860,
				"strength": 4.0000
			},
			{
				"source_id": 1144,
				"target_id": 2203,
				"strength": 8.0000
			},
			{
				"source_id": 1148,
				"target_id": 1243,
				"strength": 1.0000
			},
			{
				"source_id": 1148,
				"target_id": 1279,
				"strength": 12.0000
			},
			{
				"source_id": 1148,
				"target_id": 1444,
				"strength": 3.0000
			},
			{
				"source_id": 1148,
				"target_id": 1836,
				"strength": 18.0000
			},
			{
				"source_id": 1148,
				"target_id": 2043,
				"strength": 13.0000
			},
			{
				"source_id": 1148,
				"target_id": 2175,
				"strength": 1.0000
			},
			{
				"source_id": 1148,
				"target_id": 2511,
				"strength": 2.0000
			},
			{
				"source_id": 1148,
				"target_id": 2932,
				"strength": 1.0000
			},
			{
				"source_id": 1148,
				"target_id": 3558,
				"strength": 20.0000
			},
			{
				"source_id": 1148,
				"target_id": 4169,
				"strength": 6.0000
			},
			{
				"source_id": 1148,
				"target_id": 4266,
				"strength": 8.0000
			},
			{
				"source_id": 1148,
				"target_id": 4371,
				"strength": 10.0000
			},
			{
				"source_id": 1148,
				"target_id": 4593,
				"strength": 4.0000
			},
			{
				"source_id": 1148,
				"target_id": 4640,
				"strength": 1.0000
			},
			{
				"source_id": 1163,
				"target_id": 1860,
				"strength": 12.0000
			},
			{
				"source_id": 1163,
				"target_id": 2175,
				"strength": 1.0000
			},
			{
				"source_id": 1163,
				"target_id": 2792,
				"strength": 1.0000
			},
			{
				"source_id": 1163,
				"target_id": 3922,
				"strength": 25.0000
			},
			{
				"source_id": 1163,
				"target_id": 4640,
				"strength": 2.0000
			},
			{
				"source_id": 1163,
				"target_id": 5028,
				"strength": 1.0000
			},
			{
				"source_id": 1243,
				"target_id": 1988,
				"strength": 27.0000
			},
			{
				"source_id": 1243,
				"target_id": 2223,
				"strength": 6.0000
			},
			{
				"source_id": 1243,
				"target_id": 2511,
				"strength": 14.0000
			},
			{
				"source_id": 1243,
				"target_id": 3390,
				"strength": 29.0000
			},
			{
				"source_id": 1243,
				"target_id": 3558,
				"strength": 1.0000
			},
			{
				"source_id": 1248,
				"target_id": 1380,
				"strength": 7.0000
			},
			{
				"source_id": 1248,
				"target_id": 1900,
				"strength": 6.0000
			},
			{
				"source_id": 1248,
				"target_id": 2038,
				"strength": 6.0000
			},
			{
				"source_id": 1248,
				"target_id": 2139,
				"strength": 10.0000
			},
			{
				"source_id": 1248,
				"target_id": 2175,
				"strength": 16.0000
			},
			{
				"source_id": 1248,
				"target_id": 4068,
				"strength": 10.0000
			},
			{
				"source_id": 1248,
				"target_id": 4430,
				"strength": 8.0000
			},
			{
				"source_id": 1279,
				"target_id": 1860,
				"strength": 3.0000
			},
			{
				"source_id": 1279,
				"target_id": 2043,
				"strength": 5.0000
			},
			{
				"source_id": 1279,
				"target_id": 2203,
				"strength": 4.0000
			},
			{
				"source_id": 1380,
				"target_id": 1900,
				"strength": 19.0000
			},
			{
				"source_id": 1380,
				"target_id": 2038,
				"strength": 3.0000
			},
			{
				"source_id": 1380,
				"target_id": 2139,
				"strength": 25.0000
			},
			{
				"source_id": 1380,
				"target_id": 3616,
				"strength": 1.0000
			},
			{
				"source_id": 1380,
				"target_id": 4068,
				"strength": 28.0000
			},
			{
				"source_id": 1380,
				"target_id": 4430,
				"strength": 17.0000
			},
			{
				"source_id": 1444,
				"target_id": 1555,
				"strength": 2.0000
			},
			{
				"source_id": 1444,
				"target_id": 2548,
				"strength": 2.0000
			},
			{
				"source_id": 1444,
				"target_id": 2792,
				"strength": 2.0000
			},
			{
				"source_id": 1444,
				"target_id": 2891,
				"strength": 4.0000
			},
			{
				"source_id": 1444,
				"target_id": 2982,
				"strength": 1.0000
			},
			{
				"source_id": 1444,
				"target_id": 3536,
				"strength": 6.0000
			},
			{
				"source_id": 1444,
				"target_id": 4169,
				"strength": 3.0000
			},
			{
				"source_id": 1555,
				"target_id": 1860,
				"strength": 28.0000
			},
			{
				"source_id": 1555,
				"target_id": 1870,
				"strength": 11.0000
			},
			{
				"source_id": 1555,
				"target_id": 2023,
				"strength": 2.0000
			},
			{
				"source_id": 1555,
				"target_id": 2139,
				"strength": 20.0000
			},
			{
				"source_id": 1555,
				"target_id": 2175,
				"strength": 16.0000
			},
			{
				"source_id": 1555,
				"target_id": 2223,
				"strength": 5.0000
			},
			{
				"source_id": 1555,
				"target_id": 2797,
				"strength": 1.0000
			},
			{
				"source_id": 1555,
				"target_id": 2838,
				"strength": 28.0000
			},
			{
				"source_id": 1555,
				"target_id": 3163,
				"strength": 34.0000
			},
			{
				"source_id": 1555,
				"target_id": 3757,
				"strength": 4.0000
			},
			{
				"source_id": 1555,
				"target_id": 3922,
				"strength": 4.0000
			},
			{
				"source_id": 1555,
				"target_id": 4068,
				"strength": 10.0000
			},
			{
				"source_id": 1555,
				"target_id": 4169,
				"strength": 16.0000
			},
			{
				"source_id": 1555,
				"target_id": 4525,
				"strength": 6.0000
			},
			{
				"source_id": 1555,
				"target_id": 5028,
				"strength": 113.0000
			},
			{
				"source_id": 1555,
				"target_id": 5268,
				"strength": 3.0000
			},
			{
				"source_id": 1836,
				"target_id": 4371,
				"strength": 1.0000
			},
			{
				"source_id": 1860,
				"target_id": 1904,
				"strength": 24.0000
			},
			{
				"source_id": 1860,
				"target_id": 2023,
				"strength": 23.0000
			},
			{
				"source_id": 1860,
				"target_id": 2175,
				"strength": 14.0000
			},
			{
				"source_id": 1860,
				"target_id": 2203,
				"strength": 16.0000
			},
			{
				"source_id": 1860,
				"target_id": 2223,
				"strength": 5.0000
			},
			{
				"source_id": 1860,
				"target_id": 2536,
				"strength": 5.0000
			},
			{
				"source_id": 1860,
				"target_id": 2792,
				"strength": 1.0000
			},
			{
				"source_id": 1860,
				"target_id": 2797,
				"strength": 9.0000
			},
			{
				"source_id": 1860,
				"target_id": 2838,
				"strength": 20.0000
			},
			{
				"source_id": 1860,
				"target_id": 2891,
				"strength": 1.0000
			},
			{
				"source_id": 1860,
				"target_id": 3163,
				"strength": 7.0000
			},
			{
				"source_id": 1860,
				"target_id": 3911,
				"strength": 20.0000
			},
			{
				"source_id": 1860,
				"target_id": 3922,
				"strength": 22.0000
			},
			{
				"source_id": 1860,
				"target_id": 3939,
				"strength": 12.0000
			},
			{
				"source_id": 1860,
				"target_id": 4169,
				"strength": 17.0000
			},
			{
				"source_id": 1860,
				"target_id": 4584,
				"strength": 8.0000
			},
			{
				"source_id": 1860,
				"target_id": 4640,
				"strength": 1.0000
			},
			{
				"source_id": 1860,
				"target_id": 5158,
				"strength": 1.0000
			},
			{
				"source_id": 1870,
				"target_id": 3163,
				"strength": 12.0000
			},
			{
				"source_id": 1870,
				"target_id": 5028,
				"strength": 12.0000
			},
			{
				"source_id": 1886,
				"target_id": 5189,
				"strength": 25.0000
			},
			{
				"source_id": 1900,
				"target_id": 2038,
				"strength": 6.0000
			},
			{
				"source_id": 1900,
				"target_id": 2139,
				"strength": 34.0000
			},
			{
				"source_id": 1900,
				"target_id": 3616,
				"strength": 9.0000
			},
			{
				"source_id": 1900,
				"target_id": 4068,
				"strength": 38.0000
			},
			{
				"source_id": 1900,
				"target_id": 4430,
				"strength": 12.0000
			},
			{
				"source_id": 1904,
				"target_id": 2511,
				"strength": 1.0000
			},
			{
				"source_id": 1904,
				"target_id": 3163,
				"strength": 8.0000
			},
			{
				"source_id": 1904,
				"target_id": 3911,
				"strength": 14.0000
			},
			{
				"source_id": 1904,
				"target_id": 3939,
				"strength": 1.0000
			},
			{
				"source_id": 1988,
				"target_id": 2033,
				"strength": 4.0000
			},
			{
				"source_id": 1988,
				"target_id": 2223,
				"strength": 5.0000
			},
			{
				"source_id": 1988,
				"target_id": 2493,
				"strength": 5.0000
			},
			{
				"source_id": 1988,
				"target_id": 2511,
				"strength": 1.0000
			},
			{
				"source_id": 1988,
				"target_id": 3390,
				"strength": 32.0000
			},
			{
				"source_id": 1988,
				"target_id": 3584,
				"strength": 5.0000
			},
			{
				"source_id": 1988,
				"target_id": 4525,
				"strength": 5.0000
			},
			{
				"source_id": 2023,
				"target_id": 2139,
				"strength": 2.0000
			},
			{
				"source_id": 2023,
				"target_id": 2175,
				"strength": 1.0000
			},
			{
				"source_id": 2023,
				"target_id": 2223,
				"strength": 1.0000
			},
			{
				"source_id": 2023,
				"target_id": 3163,
				"strength": 4.0000
			},
			{
				"source_id": 2023,
				"target_id": 3922,
				"strength": 52.0000
			},
			{
				"source_id": 2023,
				"target_id": 4169,
				"strength": 1.0000
			},
			{
				"source_id": 2023,
				"target_id": 4371,
				"strength": 10.0000
			},
			{
				"source_id": 2023,
				"target_id": 5158,
				"strength": 40.0000
			},
			{
				"source_id": 2033,
				"target_id": 2041,
				"strength": 2.0000
			},
			{
				"source_id": 2033,
				"target_id": 2493,
				"strength": 17.0000
			},
			{
				"source_id": 2033,
				"target_id": 3584,
				"strength": 25.0000
			},
			{
				"source_id": 2033,
				"target_id": 4169,
				"strength": 2.0000
			},
			{
				"source_id": 2033,
				"target_id": 4525,
				"strength": 13.0000
			},
			{
				"source_id": 2038,
				"target_id": 2139,
				"strength": 6.0000
			},
			{
				"source_id": 2038,
				"target_id": 2842,
				"strength": 1.0000
			},
			{
				"source_id": 2038,
				"target_id": 4068,
				"strength": 6.0000
			},
			{
				"source_id": 2038,
				"target_id": 4126,
				"strength": 6.0000
			},
			{
				"source_id": 2038,
				"target_id": 4266,
				"strength": 4.0000
			},
			{
				"source_id": 2038,
				"target_id": 4430,
				"strength": 4.0000
			},
			{
				"source_id": 2038,
				"target_id": 5386,
				"strength": 12.0000
			},
			{
				"source_id": 2041,
				"target_id": 2797,
				"strength": 32.0000
			},
			{
				"source_id": 2041,
				"target_id": 4169,
				"strength": 31.0000
			},
			{
				"source_id": 2043,
				"target_id": 4593,
				"strength": 1.0000
			},
			{
				"source_id": 2135,
				"target_id": 2139,
				"strength": 16.0000
			},
			{
				"source_id": 2135,
				"target_id": 2792,
				"strength": 2.0000
			},
			{
				"source_id": 2135,
				"target_id": 4068,
				"strength": 14.0000
			},
			{
				"source_id": 2139,
				"target_id": 2792,
				"strength": 3.0000
			},
			{
				"source_id": 2139,
				"target_id": 3616,
				"strength": 27.0000
			},
			{
				"source_id": 2139,
				"target_id": 4068,
				"strength": 155.0000
			},
			{
				"source_id": 2139,
				"target_id": 4430,
				"strength": 19.0000
			},
			{
				"source_id": 2175,
				"target_id": 2223,
				"strength": 1.0000
			},
			{
				"source_id": 2175,
				"target_id": 3922,
				"strength": 36.0000
			},
			{
				"source_id": 2175,
				"target_id": 4068,
				"strength": 4.0000
			},
			{
				"source_id": 2175,
				"target_id": 4169,
				"strength": 23.0000
			},
			{
				"source_id": 2175,
				"target_id": 4371,
				"strength": 1.0000
			},
			{
				"source_id": 2223,
				"target_id": 2493,
				"strength": 11.0000
			},
			{
				"source_id": 2223,
				"target_id": 2536,
				"strength": 32.0000
			},
			{
				"source_id": 2223,
				"target_id": 2797,
				"strength": 1.0000
			},
			{
				"source_id": 2223,
				"target_id": 3584,
				"strength": 12.0000
			},
			{
				"source_id": 2223,
				"target_id": 4169,
				"strength": 2.0000
			},
			{
				"source_id": 2223,
				"target_id": 4525,
				"strength": 8.0000
			},
			{
				"source_id": 2223,
				"target_id": 5158,
				"strength": 1.0000
			},
			{
				"source_id": 2342,
				"target_id": 2493,
				"strength": 4.0000
			},
			{
				"source_id": 2342,
				"target_id": 2854,
				"strength": 23.0000
			},
			{
				"source_id": 2342,
				"target_id": 3584,
				"strength": 7.0000
			},
			{
				"source_id": 2342,
				"target_id": 4525,
				"strength": 1.0000
			},
			{
				"source_id": 2493,
				"target_id": 2536,
				"strength": 1.0000
			},
			{
				"source_id": 2493,
				"target_id": 2792,
				"strength": 5.0000
			},
			{
				"source_id": 2493,
				"target_id": 2842,
				"strength": 1.0000
			},
			{
				"source_id": 2493,
				"target_id": 3584,
				"strength": 59.0000
			},
			{
				"source_id": 2493,
				"target_id": 3922,
				"strength": 8.0000
			},
			{
				"source_id": 2493,
				"target_id": 4525,
				"strength": 24.0000
			},
			{
				"source_id": 2493,
				"target_id": 5189,
				"strength": 1.0000
			},
			{
				"source_id": 2511,
				"target_id": 3390,
				"strength": 12.0000
			},
			{
				"source_id": 2511,
				"target_id": 4371,
				"strength": 2.0000
			},
			{
				"source_id": 2536,
				"target_id": 3584,
				"strength": 1.0000
			},
			{
				"source_id": 2792,
				"target_id": 2891,
				"strength": 31.0000
			},
			{
				"source_id": 2792,
				"target_id": 2982,
				"strength": 5.0000
			},
			{
				"source_id": 2792,
				"target_id": 3536,
				"strength": 24.0000
			},
			{
				"source_id": 2792,
				"target_id": 3922,
				"strength": 10.0000
			},
			{
				"source_id": 2792,
				"target_id": 4126,
				"strength": 1.0000
			},
			{
				"source_id": 2792,
				"target_id": 4266,
				"strength": 1.0000
			},
			{
				"source_id": 2792,
				"target_id": 4640,
				"strength": 1.0000
			},
			{
				"source_id": 2792,
				"target_id": 4901,
				"strength": 13.0000
			},
			{
				"source_id": 2797,
				"target_id": 2932,
				"strength": 3.0000
			},
			{
				"source_id": 2797,
				"target_id": 4169,
				"strength": 92.0000
			},
			{
				"source_id": 2797,
				"target_id": 5386,
				"strength": 3.0000
			},
			{
				"source_id": 2838,
				"target_id": 3163,
				"strength": 3.0000
			},
			{
				"source_id": 2838,
				"target_id": 3757,
				"strength": 1.0000
			},
			{
				"source_id": 2838,
				"target_id": 3922,
				"strength": 2.0000
			},
			{
				"source_id": 2838,
				"target_id": 4584,
				"strength": 20.0000
			},
			{
				"source_id": 2838,
				"target_id": 5028,
				"strength": 9.0000
			},
			{
				"source_id": 2842,
				"target_id": 2932,
				"strength": 20.0000
			},
			{
				"source_id": 2842,
				"target_id": 3584,
				"strength": 1.0000
			},
			{
				"source_id": 2842,
				"target_id": 4126,
				"strength": 1.0000
			},
			{
				"source_id": 2842,
				"target_id": 4266,
				"strength": 4.0000
			},
			{
				"source_id": 2842,
				"target_id": 4371,
				"strength": 33.0000
			},
			{
				"source_id": 2842,
				"target_id": 5386,
				"strength": 5.0000
			},
			{
				"source_id": 2891,
				"target_id": 2982,
				"strength": 1.0000
			},
			{
				"source_id": 2891,
				"target_id": 3536,
				"strength": 30.0000
			},
			{
				"source_id": 2891,
				"target_id": 3922,
				"strength": 3.0000
			},
			{
				"source_id": 2891,
				"target_id": 4640,
				"strength": 2.0000
			},
			{
				"source_id": 2891,
				"target_id": 4901,
				"strength": 13.0000
			},
			{
				"source_id": 2891,
				"target_id": 5189,
				"strength": 1.0000
			},
			{
				"source_id": 2932,
				"target_id": 4126,
				"strength": 2.0000
			},
			{
				"source_id": 2932,
				"target_id": 4169,
				"strength": 1.0000
			},
			{
				"source_id": 2932,
				"target_id": 4266,
				"strength": 3.0000
			},
			{
				"source_id": 2932,
				"target_id": 4371,
				"strength": 24.0000
			},
			{
				"source_id": 2932,
				"target_id": 5386,
				"strength": 7.0000
			},
			{
				"source_id": 2982,
				"target_id": 3536,
				"strength": 1.0000
			},
			{
				"source_id": 3163,
				"target_id": 3911,
				"strength": 8.0000
			},
			{
				"source_id": 3163,
				"target_id": 3922,
				"strength": 3.0000
			},
			{
				"source_id": 3163,
				"target_id": 3939,
				"strength": 3.0000
			},
			{
				"source_id": 3163,
				"target_id": 4525,
				"strength": 4.0000
			},
			{
				"source_id": 3163,
				"target_id": 5028,
				"strength": 26.0000
			},
			{
				"source_id": 3536,
				"target_id": 4640,
				"strength": 5.0000
			},
			{
				"source_id": 3536,
				"target_id": 4901,
				"strength": 56.0000
			},
			{
				"source_id": 3558,
				"target_id": 4371,
				"strength": 7.0000
			},
			{
				"source_id": 3584,
				"target_id": 4169,
				"strength": 2.0000
			},
			{
				"source_id": 3584,
				"target_id": 4525,
				"strength": 24.0000
			},
			{
				"source_id": 3584,
				"target_id": 5189,
				"strength": 1.0000
			},
			{
				"source_id": 3616,
				"target_id": 4068,
				"strength": 27.0000
			},
			{
				"source_id": 3757,
				"target_id": 5028,
				"strength": 16.0000
			},
			{
				"source_id": 3757,
				"target_id": 5268,
				"strength": 13.0000
			},
			{
				"source_id": 3911,
				"target_id": 3939,
				"strength": 2.0000
			},
			{
				"source_id": 3922,
				"target_id": 4169,
				"strength": 4.0000
			},
			{
				"source_id": 3922,
				"target_id": 4640,
				"strength": 2.0000
			},
			{
				"source_id": 3922,
				"target_id": 5028,
				"strength": 1.0000
			},
			{
				"source_id": 3922,
				"target_id": 5158,
				"strength": 13.0000
			},
			{
				"source_id": 4068,
				"target_id": 4169,
				"strength": 3.0000
			},
			{
				"source_id": 4068,
				"target_id": 4430,
				"strength": 20.0000
			},
			{
				"source_id": 4126,
				"target_id": 4266,
				"strength": 18.0000
			},
			{
				"source_id": 4126,
				"target_id": 4371,
				"strength": 7.0000
			},
			{
				"source_id": 4126,
				"target_id": 4640,
				"strength": 4.0000
			},
			{
				"source_id": 4169,
				"target_id": 4371,
				"strength": 6.0000
			},
			{
				"source_id": 4169,
				"target_id": 5386,
				"strength": 9.0000
			},
			{
				"source_id": 4266,
				"target_id": 4371,
				"strength": 5.0000
			},
			{
				"source_id": 4266,
				"target_id": 4593,
				"strength": 3.0000
			},
			{
				"source_id": 4266,
				"target_id": 4640,
				"strength": 1.0000
			},
			{
				"source_id": 4266,
				"target_id": 5386,
				"strength": 2.0000
			},
			{
				"source_id": 4371,
				"target_id": 4593,
				"strength": 6.0000
			},
			{
				"source_id": 4371,
				"target_id": 4640,
				"strength": 1.0000
			},
			{
				"source_id": 4371,
				"target_id": 5158,
				"strength": 7.0000
			},
			{
				"source_id": 4371,
				"target_id": 5327,
				"strength": 1.0000
			},
			{
				"source_id": 4371,
				"target_id": 5386,
				"strength": 10.0000
			},
			{
				"source_id": 4525,
				"target_id": 5028,
				"strength": 1.0000
			},
			{
				"source_id": 4593,
				"target_id": 4640,
				"strength": 1.0000
			},
			{
				"source_id": 4640,
				"target_id": 4901,
				"strength": 5.0000
			},
			{
				"source_id": 5028,
				"target_id": 5268,
				"strength": 21.0000
			}
		]
	}
}
